MANIFEST.in
setup.cfg
setup.py
sculpt/__init__.py
sculpt.common.egg-info/PKG-INFO
sculpt.common.egg-info/SOURCES.txt
sculpt.common.egg-info/dependency_links.txt
sculpt.common.egg-info/top_level.txt
sculpt/common/__init__.py
sculpt/common/enumeration.py
sculpt/common/parameter_proxy.py
sculpt/common/settings_common.py
sculpt/common/settings_logging.py